<?xml version="1.0"?>
<!DOCTYPE hibernate-mapping PUBLIC "-//Hibernate/Hibernate Mapping DTD 3.0//EN"
"http://hibernate.sourceforge.net/hibernate-mapping-3.0.dtd">
<!-- Generated 9-apr-2008 12.18.26 by Hibernate Tools 3.1.0 beta3 -->
<hibernate-mapping>
    <class name="it.eng.spagobi.wapp.metadata.SbiMenuRole" table="sbi_menu_role">
        <composite-id name="id" class="it.eng.spagobi.wapp.metadata.SbiMenuRoleId">
            <key-property name="menuId" type="integer">
                <column name="menu_id" />
            </key-property>
            <key-property name="extRoleId" type="integer">
                <column name="ext_role_id" />
            </key-property>
        </composite-id>
        <many-to-one name="sbiMenu" class="it.eng.spagobi.wapp.metadata.SbiMenu" update="false" insert="false" fetch="select">
            <column name="menu_id" not-null="true" />
        </many-to-one>
        <many-to-one name="sbiExtRoles" class="it.eng.spagobi.commons.metadata.SbiExtRoles" update="false" insert="false" fetch="select">
            <column name="ext_role_id" not-null="true" />
        </many-to-one>
    </class>
</hibernate-mapping>
